<?xml version="1.0" encoding="utf-8" ?>
<!--****供应商退款****-->
<MessageResource>
  <MessageList>
    <Message name="VendorRefund_SysNoEmpty">供应商退款编号无效!</Message>
    <Message name="VendorRefund_RefundNotExist">供应商退款单在数据库中不存在!</Message>
    <Message name="VendorRefund_Abandon_Invalid">该供应商退款单为作废状态,不允许进行当前操作！</Message>
    <Message name="VendorRefund_Origin_Invalid">该供应商退款单为初始状态,不允许进行当前操作！</Message>
    <Message name="VendorRefund_PMDVerify_Invalid">该供应商退款单为PMD审核状态,不允许进行当前操作！</Message>
    <Message name="VendorRefund_CannotOperate">您不是当前产品的PM，也不是当前产品PM的备份PM，无法操作!</Message>
    <Message name="VendorRefund_CloseInvalid">单件编号为:{0} 的状态不在处理中,不允许进行关闭单件的操作!</Message>
    <Message name="VendorRefund_OperatorCannotSame_Invalid">创建人，PM审核人，PMD审核人，PMCC审核人，不能相同</Message>
  </MessageList>
</MessageResource>
