<?xml version="1.0" encoding="utf-8" ?>
<!--****虚库采购单****-->
<MessageResource>
  <MessageList>
    <Message name="VSPO_ItemSysNoEmpty">销售单Item编号不能为空！</Message>
    <Message name="VSPO_CannotCreateVSPO">不能再生成虚库商品采购单！</Message>
    <Message name="VSPO_OrderSysNoEmpty">单据号不能为空！</Message>
    <Message name="VSPO_EATimeEmpty">估计到达时间不能为空！</Message>
    <Message name="VSPO_EATLongTimeEmpty">预计到货时间 - 小时分 不能为空!！</Message>
    <Message name="VSPO_ShiftSysNoFormatWrong">移仓单号格式不正确！</Message>
    <Message name="VSPO_ConvertSysNoFormatWrong">转换单号格式不正确！</Message>
    <Message name="VSPO_POSysNoFormatWrong">采购单号格式不正确！</Message>
    <Message name="VSPO_AbandonVSPO_Invalid_Update">虚库采购单为作废状态，不能更新！</Message>

    <Message name="VSPO_PONotFound">在您输入的采购单中找不到对应的商品或该采购单已经作废！</Message>
    <Message name="VSPO_ShiftNotFound">在您输入的移仓单中找不到对应的商品或该移仓单已经作废！</Message>
    <Message name="VSPO_ConvertNotFound">在您输入的转换单中找不到对应的商品或该转换单已经作废！</Message>
    <Message name="VSPO_VSPOSysNoEmpty">虚库采购单的编号不能为空！</Message>
    <Message name="VSPO_CSMemoEmpty">CS备注不能为空！</Message>
    <Message name="VSPO_VSPONotFound">该虚库采购单在数据中不存在,操作失败!</Message>
    <Message name="VSPO_Abandon_Invalid_Abandon">虚库采购单为作废状态，不能再作废!</Message>
    <Message name="VSPO_OutStock_Note">请注意：对应的移仓单已出库!</Message>


    <Message name="VSPO_UpdateVSPO_POMemo">更新虚库采购单{0},PM更新备注</Message>
    <Message name="VSPO_UpdateVSPO_CSMemo">虚库采购单CS备注更新</Message>
    <Message name="VSPO_UpdateVSPO_Abandon">作废虚库采购单</Message>
    <Message name="VSPO_UpdateVSPO_ETA">更新虚库采购单{0} ,输入采购单号和预计到货时间</Message>

  </MessageList>
</MessageResource>